Metadata-Version: 1.1
Name: easy-kubernetes
Version: 0.1.0
Summary: A python module to interact with kubernetes REST API.
Home-page: https://github.com/GoDllkE/python-api-kubernetes
Author: Gustavo Toledo de Oliveira
Author-email: gustavot53@gmail.com
License: UNKNOWN
Download-URL: https://github.com/GoDllkE/Easy-Kubernetes/archive/master.zip
Project-URL: Source, https://github.com/GoDllkE/python-api-kubernetes
Project-URL: Documentation, https://github.com/GoDllkE/python-api-kubernetes/docs
Project-URL: Tracker, https://github.com/GoDllkE/python-api-kubernetes/issues
Keywords: kubernetes,origin,easy-kubernetes,kubernetes api,python kubernetes,kubectl.py
Platform: UNKNOWN
Classifier: Intended Audience :: Developers
Classifier: Operating System :: OS Independent
Classifier: License :: OSI Approved :: GNU General Public License v3 (GPLv3)
Classifier: Natural Language :: Portuguese (Brazilian)
Classifier: Programming Language :: Python :: 3.4
Classifier: Programming Language :: Python :: 3.5
Classifier: Programming Language :: Python :: 3.6
Classifier: Programming Language :: Python :: 3.7
Classifier: Programming Language :: Python :: 3 :: Only
